penv/__init__.py
penv/base.py
penv/bash.py
penv/cli.py
penv/conf.py
penv/plugins.py
penv/shell.py
penv_contrib/__init__.py
penv_contrib/register.py
penv-1.2.dist-info/METADATA
penv-1.2.dist-info/WHEEL
penv-1.2.dist-info/entry_points.txt
penv-1.2.dist-info/top_level.txt
penv-1.2.dist-info/RECORD
