Metadata-Version: 1.1
Name: penv
Version: 1.2
Summary: Framework for ease project management tools building.
Home-page: https://github.com/jqb/penv/tree/ver-1.2
Author: Jakub Janoszek
Author-email: kuba.janoszek@gmail.com
License: UNKNOWN
Platform: UNKNOWN
Classifier: Development Status :: 4 - Beta
Classifier: Environment :: Web Environment
Classifier: Intended Audience :: Developers
Classifier: License :: OSI Approved :: BSD License
Classifier: Operating System :: OS Independent
Classifier: Programming Language :: Python
